brick_game/__init__.py
brick_game/enemy_class.py
brick_game/global_variables.py
brick_game/main_file.py
brick_game/misc.py
brick_game/player_class.py
brick_game-0.1.2.dist-info/LICENSE
brick_game-0.1.2.dist-info/METADATA
brick_game-0.1.2.dist-info/WHEEL
brick_game-0.1.2.dist-info/entry_points.txt
brick_game-0.1.2.dist-info/top_level.txt
brick_game-0.1.2.dist-info/RECORD
